tgen/__init__.py
tgen/py.typed
tgen-0.3.0.dist-info/METADATA
tgen-0.3.0.dist-info/WHEEL
tgen-0.3.0.dist-info/RECORD
