Metadata-Version: 2.1
Name: tgen
Version: 0.3.0
Summary: A pretty simple text generation library
Author: arslee07
Author-email: mail@arslee.me
Requires-Python: >=3.10,<4.0
Classifier: Programming Language :: Python :: 3
Classifier: Programming Language :: Python :: 3.10
Classifier: Programming Language :: Python :: 3.11
Requires-Dist: u-msgpack-python (>=2.7.2,<3.0.0)
